tinyalchemy/__init__.py
tinyalchemy/py.typed
tinyalchemy/table.py
tinyalchemy-0.0.1.dist-info/LICENSE
tinyalchemy-0.0.1.dist-info/METADATA
tinyalchemy-0.0.1.dist-info/WHEEL
tinyalchemy-0.0.1.dist-info/top_level.txt
tinyalchemy-0.0.1.dist-info/RECORD
